libchickadee/__init__.py
libchickadee/chickadee.py
libchickadee/update.py
libchickadee/backends/__init__.py
libchickadee/backends/ipapi.py
libchickadee/parsers/__init__.py
libchickadee/parsers/evtx.py
libchickadee/parsers/plain_text.py
libchickadee/parsers/xlsx.py
libchickadee/resolvers/__init__.py
libchickadee/resolvers/ipapi.py
libchickadee/resolvers/iptoasn.py
libchickadee/resolvers/virustotal.py
libchickadee/test/__init__.py
libchickadee/test/test_backend_ipapi.py
libchickadee/test/test_chickadee.py
libchickadee/test/test_iptoasn.py
libchickadee/test/test_parser_base.py
libchickadee/test/test_parser_evtx.py
libchickadee/test/test_parser_plaintext.py
libchickadee/test/test_parser_xlsx.py
libchickadee/test/test_resolver_ipapi.py
libchickadee/test/test_resolver_virustotal.py
libchickadee/test/test_updates.py
chickadee-20210314.1.dist-info/LICENSE
chickadee-20210314.1.dist-info/METADATA
chickadee-20210314.1.dist-info/WHEEL
chickadee-20210314.1.dist-info/entry_points.txt
chickadee-20210314.1.dist-info/top_level.txt
chickadee-20210314.1.dist-info/RECORD
