Metadata-Version: 2.1
Name: chickadee
Version: 20210314.1
Summary: Yet another GeoIP resolution tool.
Home-page: https://github.com/chapinb/chickadee
Author: Chapin Bryce
Author-email: python@chapinb.com
License: UNKNOWN
Platform: UNKNOWN
Classifier: Programming Language :: Python :: 3.5
Classifier: Programming Language :: Python :: 3.6
Classifier: Programming Language :: Python :: 3.7
Classifier: Programming Language :: Python :: 3.8
Classifier: Programming Language :: Python :: 3 :: Only
Classifier: License :: OSI Approved :: MIT License
Classifier: Operating System :: OS Independent
Classifier: Development Status :: 5 - Production/Stable
Classifier: Environment :: Console
Classifier: Intended Audience :: Telecommunications Industry
Classifier: Intended Audience :: System Administrators
Classifier: Intended Audience :: Other Audience
Classifier: Intended Audience :: Information Technology
Classifier: Intended Audience :: Developers
Classifier: Intended Audience :: Education
Classifier: Natural Language :: English
Classifier: Topic :: Scientific/Engineering :: Information Analysis
Classifier: Topic :: Security
Classifier: Topic :: Utilities
Requires-Dist: requests (>=2.22.0)
Requires-Dist: openpyxl (~=2.6.3)
Requires-Dist: tqdm (~=4.36.1)
Requires-Dist: netaddr (~=0.7.19)
Requires-Dist: python-evtx (~=0.6.1)
